Metadata-Version: 2.1
Name: adversarial-test
Version: 0.1.4
Summary: Adversarial test for tabular data
Author: TuHM
Project-URL: GitHub, https://github.com/hmtu14/adversarial-test
